PCF8574.py
pcf8574_library-0.0.2.dist-info/LICENSE.md
pcf8574_library-0.0.2.dist-info/METADATA
pcf8574_library-0.0.2.dist-info/WHEEL
pcf8574_library-0.0.2.dist-info/top_level.txt
pcf8574_library-0.0.2.dist-info/RECORD
