Metadata-Version: 2.1
Name: pcf8574-library
Version: 0.0.2
Summary: Most starred PCF8574 library. i2c digital expander for Arduino, Raspberry Pi Pico and rp2040 boards, esp32, SMT32 and ESP8266. Can read write digital values with only 2 wire. Very simple to use
Home-page: https://github.com/xreef/PCF8574_micropython_library
Author: Renzo Mischianti
Author-email: Renzo Mischianti <renzo@mischianti.org>
Maintainer: Renzo Mischianti
Maintainer-email: Renzo Mischianti <renzo@mischianti.org>
License: The MIT License (MIT)
Project-URL: homepage, https://www.mischianti.org
Project-URL: Documentation, https://www.mischianti.org/category/my-libraries/pcf8574/
Project-URL: Documentazione, https://www.mischianti.org/it/category/le-mie-librerie/pcf8574-it/
Project-URL: Repository, https://github.com/xreef/PCF8574_micropython_library
Project-URL: Bug Tracker, https://github.com/xreef/PCF8574_micropython_library/issues
Project-URL: Examples, https://github.com/xreef/PCF8574_micropython_library/tree/master/examples
Keywords: micropython,digital,i2c,encoder,expander,pcf8574,pcf8574a,esp32,esp8266,stm32,SAMD,Arduino,wire,rp2040,Raspberry
Classifier: Development Status :: 5 - Production/Stable
Classifier: Programming Language :: Python :: Implementation :: MicroPython
Classifier: License :: OSI Approved :: MIT License
Requires-Python: >=3.7
License-File: LICENSE.md
